{"cameraMode":{"drawMode":0,"name":"Shaded","section":"Shading Mode"},"sceneLighting":true,"audioPlay":false,"sceneViewState":{"m_AlwaysRefresh":false,"showFog":true,"showSkybox":true,"showFlares":true,"showImageEffects":true,"showParticleSystems":true,"showVisualEffectGraphs":true,"m_FxEnabled":true},"in2DMode":false,"pivot":{"x":0.0,"y":0.20000000298023225,"z":0.0},"rotation":{"x":0.047810349613428119,"y":0.8545645475387573,"z":-0.07996991276741028,"w":0.5108585953712463},"size":20.3652286529541,"orthographic":false}